barkprints/__init__.py
barkprints/__main__.py
barkprints/corpus.py
barkprints/corpus_builder.py
barkprints/corpus_loader.py
barkprints/embedding_matcher.py
barkprints/feature_extractor.py
barkprints/text_generator.py
barkprints/corpora/literature.npz
barkprints/corpora/nature.npz
barkprints-0.1.0.dist-info/METADATA
barkprints-0.1.0.dist-info/WHEEL
barkprints-0.1.0.dist-info/entry_points.txt
barkprints-0.1.0.dist-info/licenses/LICENSE
barkprints-0.1.0.dist-info/RECORD
