Metadata-Version: 2.4
Name: barkprints
Version: 0.1.0
Summary: Generate poetry and text from tree bark images using deterministic feature mapping
Author-email: Martin <martin@example.com>
License: MIT
License-File: LICENSE
Requires-Python: >=3.10
Requires-Dist: numpy>=1.24.0
Requires-Dist: pillow>=10.0.0
Requires-Dist: scipy>=1.10.0
Requires-Dist: sentence-transformers>=2.2.0
